{"Animal": 5, "Book": 3, "Building": 1, "Butterfly": 1, "Cat": 1, "Clothing": 5, "Dinosaur": 2, "Door": 2, "Fashion accessory": 2, "Fish": 2, "Flower": 13, "Food": 3, "Fruit": 1, "Human eye": 2, "Human face": 3, "Human head": 3, "Insect": 2, "Invertebrate": 2, "Mammal": 5, "Marine invertebrates": 1, "Moths and butterflies": 1, "Mushroom": 2, "Person": 5, "Picture frame": 4, "Pineapple": 1, "Plant": 5, "Poster": 4, "Reptile": 1, "Rose": 6, "Sculpture": 1, "Shellfish": 1, "Skull": 2, "Snack": 1, "Tortoise": 1, "Tree": 2, "Vegetable": 3, "Window": 1}