{"Aircraft": 2, "Airplane": 3, "Barge": 1, "Billboard": 1, "Boat": 5, "Book": 1, "Canoe": 1, "Car": 4, "Clothing": 14, "Dress": 1, "Fashion accessory": 7, "Flag": 3, "Flower": 1, "Footwear": 1, "Furniture": 1, "Girl": 1, "Helicopter": 1, "Human arm": 4, "Human body": 2, "Human ear": 1, "Human eye": 2, "Human face": 1, "Human hair": 3, "Human head": 1, "Human mouth": 1, "Human nose": 1, "Jacket": 1, "Jet ski": 1, "Land vehicle": 4, "Mammal": 1, "Man": 1, "Office building": 1, "Office supplies": 1, "Person": 3, "Poster": 2, "Sports equipment": 3, "Surfboard": 2, "Swimming pool": 1, "Table": 2, "Toy": 3, "Vehicle": 5, "Watercraft": 4, "Woman": 1}