{"Aircraft": 3, "Airplane": 1, "Auto part": 8, "Book": 2, "Car": 1, "Chair": 2, "Clothing": 6, "Cosmetics": 1, "Cutting board": 1, "Dagger": 3, "Envelope": 2, "Fast food": 1, "Flashlight": 1, "Food": 2, "Furniture": 2, "Human arm": 4, "Kitchen knife": 4, "Knife": 3, "Land vehicle": 1, "Laptop": 1, "Lipstick": 1, "Man": 2, "Medical equipment": 1, "Musical instrument": 1, "Office supplies": 5, "Pen": 1, "Person": 5, "Poster": 1, "Ring binder": 3, "Rocket": 1, "Scissors": 2, "Shotgun": 2, "Skateboard": 2, "Snack": 1, "Stapler": 1, "Suit": 2, "Sword": 4, "Syringe": 1, "Table": 4, "Tire": 1, "Tool": 2, "Toothbrush": 1, "Toy": 1, "Vehicle": 1, "Weapon": 2, "Wheel": 1, "Window": 1, "Wrench": 1}