{"Auto part": 1, "Billboard": 3, "Book": 1, "Calculator": 1, "Camera": 1, "Clothing": 5, "Computer keyboard": 1, "Computer monitor": 4, "Flag": 1, "Home appliance": 1, "Human arm": 10, "Human body": 3, "Human hand": 9, "Human leg": 1, "Land vehicle": 1, "Laptop": 3, "Man": 6, "Medical equipment": 2, "Mobile phone": 5, "Office supplies": 1, "Person": 13, "Picture frame": 1, "Plant": 2, "Poster": 6, "Scoreboard": 6, "Sports equipment": 1, "Tablet computer": 4, "Television": 4, "Toy": 2, "Woman": 1}