{"Airplane": 1, "Animal": 2, "Bird": 3, "Boat": 2, "Car": 1, "Carnivore": 1, "Clothing": 1, "Dolphin": 1, "Fish": 3, "Footwear": 2, "Fountain": 1, "Harbor seal": 3, "Hippopotamus": 1, "House": 1, "Human arm": 2, "Human foot": 1, "Human hand": 3, "Human leg": 2, "Land vehicle": 1, "Mammal": 1, "Man": 1, "Marine mammal": 3, "Otter": 1, "Penguin": 1, "Person": 1, "Plant": 16, "Poster": 4, "Reptile": 1, "Sculpture": 1, "Sea lion": 2, "Shark": 1, "Squid": 1, "Surfboard": 1, "Swimming pool": 1, "Tree": 25, "Vehicle": 3, "Watercraft": 1, "Whale": 2, "Window": 1}