{"Auto part": 1, "Book": 1, "Building": 2, "Cabinetry": 2, "Car": 1, "Chair": 8, "Clothing": 1, "Coffee table": 1, "Computer keyboard": 2, "Computer monitor": 3, "Couch": 1, "Desk": 8, "Door": 3, "Fast food": 1, "Furniture": 14, "Home appliance": 1, "House": 1, "Kitchen appliance": 1, "Land vehicle": 2, "Laptop": 1, "Man": 2, "Medical equipment": 2, "Office building": 4, "Office supplies": 2, "Person": 3, "Poster": 2, "Shelf": 8, "Table": 13, "Tableware": 1, "Television": 2, "Train": 3, "Vehicle": 2, "Window": 1}