{"Aircraft": 1, "Animal": 1, "Auto part": 4, "Balloon": 2, "Bicycle": 1, "Book": 2, "Car": 1, "Chopsticks": 1, "Clothing": 2, "Corded phone": 1, "Door handle": 1, "Drinking straw": 2, "Fashion accessory": 3, "Fish": 1, "Flashlight": 3, "Furniture": 1, "Glasses": 1, "Hand dryer": 1, "Headphones": 3, "Human head": 1, "Invertebrate": 1, "Lamp": 5, "Land vehicle": 2, "Marine invertebrates": 1, "Medical equipment": 5, "Microphone": 1, "Mirror": 2, "Musical instrument": 3, "Office supplies": 3, "Parachute": 1, "Pen": 1, "Picture frame": 1, "Plumbing fixture": 1, "Poster": 3, "Scissors": 1, "Screwdriver": 2, "Seat belt": 1, "Sewing machine": 2, "Shellfish": 1, "Shotgun": 1, "Skateboard": 1, "Sports equipment": 1, "Squid": 1, "Stapler": 3, "Table": 2, "Telephone": 1, "Tool": 5, "Toy": 2, "Turtle": 1, "Vehicle": 4, "Violin": 2, "Weapon": 4, "Whisk": 1, "Window": 1}