{"Bird": 2, "Book": 2, "Building": 4, "Cake": 1, "Christmas tree": 1, "Clothing": 4, "Computer keyboard": 5, "Desk": 1, "Envelope": 2, "Flag": 7, "Flower": 4, "Food": 2, "Fountain": 1, "Furniture": 4, "Guitar": 2, "House": 2, "Houseplant": 1, "Human body": 1, "Human face": 2, "Human hair": 1, "Human hand": 5, "Human head": 1, "Lamp": 1, "Laptop": 2, "Maple": 1, "Mobile phone": 3, "Musical instrument": 2, "Musical keyboard": 1, "Office supplies": 1, "Person": 3, "Piano": 1, "Picture frame": 1, "Plant": 8, "Poster": 7, "Sports equipment": 1, "Stairs": 1, "Swimming pool": 1, "Table": 4, "Tower": 1, "Toy": 1, "Tree": 2, "Vehicle": 2, "Wine rack": 1}