{"Bookcase": 2, "Building": 1, "Cabinetry": 1, "Chair": 2, "Chest of drawers": 1, "Clothing": 8, "Coffee table": 1, "Desk": 4, "Door": 1, "Drawer": 1, "Filing cabinet": 1, "Furniture": 15, "House": 1, "Human arm": 6, "Human body": 2, "Human face": 2, "Human hair": 2, "Human hand": 5, "Human head": 2, "Human nose": 1, "Kitchen appliance": 3, "Laptop": 1, "Man": 4, "Medical equipment": 1, "Mobile phone": 1, "Office building": 2, "Person": 6, "Plumbing fixture": 1, "Shelf": 8, "Shirt": 1, "Suit": 1, "Table": 7, "Tableware": 2, "Window": 1, "Woman": 2}