{"Baked goods": 1, "Book": 1, "Bowl": 1, "Box": 2, "Cake": 1, "Camera": 4, "Car": 3, "Chair": 1, "Clothing": 1, "Coffee table": 1, "Computer keyboard": 1, "Dairy": 1, "Dessert": 1, "Fashion accessory": 1, "Fast food": 1, "Flowerpot": 1, "Food": 6, "Footwear": 1, "Furniture": 5, "Handbag": 1, "Home appliance": 2, "Human arm": 5, "Human hand": 4, "Ipod": 3, "Kitchen appliance": 1, "Laptop": 3, "Man": 1, "Mobile phone": 8, "Office supplies": 5, "Person": 5, "Picture frame": 1, "Plant": 3, "Plate": 1, "Platter": 1, "Scale": 1, "Sculpture": 1, "Serving tray": 1, "Shelf": 1, "Snack": 1, "Table": 5, "Tablet computer": 4, "Tableware": 2, "Toy": 3, "Watch": 3}