{"Baked goods": 1, "Billboard": 3, "Boat": 1, "Book": 1, "Clothing": 11, "Computer monitor": 1, "Doll": 1, "Dress": 1, "Fashion accessory": 6, "Fast food": 2, "Flag": 1, "Food": 8, "Fruit": 1, "Furniture": 1, "Girl": 1, "Human arm": 7, "Human body": 1, "Human eye": 5, "Human face": 2, "Human hair": 4, "Human hand": 2, "Human head": 2, "Human mouth": 2, "Human nose": 1, "Laptop": 1, "Mammal": 1, "Man": 3, "Office supplies": 1, "Person": 5, "Picture frame": 1, "Plant": 3, "Poster": 7, "Scoreboard": 1, "Snack": 2, "Television": 3, "Toy": 3, "Whiteboard": 1, "Woman": 2}