{"Aircraft": 1, "Airplane": 2, "Auto part": 2, "Balloon": 2, "Bicycle": 2, "Bicycle wheel": 2, "Book": 2, "Bowling equipment": 2, "Cake": 1, "Candle": 1, "Candy": 1, "Car": 1, "Chopsticks": 1, "Christmas tree": 2, "Clothing": 6, "Drink": 2, "Drinking straw": 2, "Fashion accessory": 2, "Fish": 1, "Flag": 2, "Flower": 2, "Food": 1, "Goggles": 1, "Guitar": 2, "Headphones": 1, "Houseplant": 1, "Human head": 1, "Lamp": 2, "Land vehicle": 2, "Lantern": 2, "Light bulb": 1, "Maple": 1, "Medical equipment": 1, "Musical instrument": 2, "Office supplies": 3, "Palm tree": 1, "Person": 4, "Plant": 3, "Poster": 2, "Pumpkin": 1, "Reptile": 1, "Sculpture": 1, "Skateboard": 2, "Sports equipment": 2, "Sword": 1, "Table": 3, "Tire": 1, "Tool": 1, "Tower": 1, "Toy": 2, "Traffic sign": 2, "Tree": 1, "Tree house": 1, "Umbrella": 3, "Vehicle": 2, "Weapon": 2, "Wheel": 2, "Wine glass": 1}