{"Aircraft": 1, "Airplane": 1, "Auto part": 3, "Band-aid": 1, "Bicycle": 2, "Bicycle wheel": 1, "Billboard": 1, "Boat": 2, "Book": 1, "Building": 8, "Cake": 1, "Car": 1, "Christmas tree": 1, "Clothing": 2, "Curtain": 1, "Flag": 3, "Flower": 1, "Furniture": 1, "Guitar": 2, "House": 5, "Human hand": 1, "Ladder": 1, "Lamp": 1, "Land vehicle": 3, "Mirror": 1, "Musical instrument": 1, "Parachute": 1, "Picture frame": 1, "Plant": 3, "Poster": 4, "Scoreboard": 1, "Skyscraper": 5, "Sports equipment": 1, "Stairs": 4, "Swimming pool": 1, "Table": 1, "Tire": 1, "Tower": 3, "Toy": 1, "Traffic sign": 1, "Train": 1, "Tree": 4, "Vehicle": 4, "Watercraft": 3, "Wheel": 3, "Window": 9, "Window blind": 1}