{"Billboard": 1, "Building": 2, "Chair": 2, "Clothing": 8, "Computer monitor": 2, "Convenience store": 1, "Flag": 1, "Furniture": 9, "Girl": 3, "Human arm": 3, "Human body": 3, "Human face": 4, "Human hair": 5, "Human head": 4, "Human leg": 1, "Jeans": 1, "Land vehicle": 2, "Laptop": 1, "Man": 6, "Medical equipment": 2, "Office building": 1, "Office supplies": 2, "Person": 15, "Sculpture": 1, "Shelf": 1, "Sports equipment": 1, "Suit": 2, "Table": 2, "Toy": 3, "Vehicle": 3, "Waste container": 1, "Woman": 7}