{"Bottle": 1, "Brassiere": 1, "Building": 2, "Chair": 1, "Clothing": 7, "Doll": 1, "Dress": 3, "Drink": 10, "Fashion accessory": 2, "Footwear": 1, "Furniture": 3, "Girl": 1, "Glasses": 1, "Guitar": 1, "Human arm": 9, "Human body": 3, "Human eye": 4, "Human face": 2, "Human hair": 5, "Human hand": 3, "Human head": 2, "Human mouth": 1, "Human nose": 2, "Mammal": 3, "Man": 2, "Musical instrument": 1, "Person": 4, "Poster": 1, "Shirt": 1, "Skyscraper": 5, "Suit": 1, "Swimwear": 1, "Table": 5, "Tableware": 1, "Tower": 5, "Toy": 1, "Wine": 1, "Woman": 2}