{"Auto part": 3, "Book": 1, "Building": 1, "Car": 1, "Chair": 1, "Clothing": 14, "Curtain": 1, "Dress": 1, "Fashion accessory": 1, "Flag": 3, "Furniture": 6, "Girl": 2, "Guitar": 1, "Human arm": 4, "Human body": 5, "Human face": 4, "Human hair": 4, "Human head": 3, "Land vehicle": 2, "Mammal": 3, "Man": 4, "Medical equipment": 1, "Microphone": 1, "Musical instrument": 1, "Office supplies": 1, "Person": 8, "Poster": 4, "Skyscraper": 1, "Surfboard": 1, "Table": 5, "Tie": 1, "Tower": 1, "Toy": 1, "Vehicle": 2, "Wheel": 4, "Window": 1, "Woman": 2}