{"Auto part": 2, "Bathroom accessory": 1, "Bowling equipment": 2, "Boy": 1, "Calculator": 1, "Camera": 2, "Car": 1, "Cassette deck": 3, "Clothing": 6, "Coffeemaker": 2, "Computer monitor": 1, "Corded phone": 2, "Door": 2, "Flashlight": 1, "Furniture": 3, "Girl": 1, "Hand dryer": 2, "Headphones": 1, "Home appliance": 3, "Human body": 2, "Human ear": 1, "Human eye": 3, "Human face": 2, "Human hair": 3, "Human head": 3, "Human nose": 4, "Ipod": 1, "Kitchen appliance": 1, "Laptop": 1, "Mammal": 2, "Man": 2, "Medical equipment": 2, "Microwave oven": 2, "Mobile phone": 2, "Musical instrument": 1, "Office supplies": 1, "Oven": 1, "Parking meter": 2, "Person": 6, "Plant": 1, "Poster": 2, "Power plugs and sockets": 1, "Remote control": 1, "Suit": 1, "Telephone": 1, "Television": 1, "Tree": 5, "Vehicle": 1, "Washing machine": 3, "Window": 2, "Woman": 2}