{"Airplane": 1, "Billboard": 1, "Boat": 1, "Building": 4, "Car": 2, "Chair": 2, "Clothing": 7, "Dress": 2, "Footwear": 1, "Furniture": 3, "Girl": 3, "Human arm": 4, "Human body": 3, "Human face": 2, "Human hair": 2, "Human head": 2, "Human leg": 1, "Land vehicle": 2, "Mammal": 2, "Man": 2, "Medical equipment": 1, "Mirror": 1, "Office supplies": 1, "Person": 7, "Picture frame": 1, "Poster": 2, "Skyscraper": 13, "Table": 3, "Television": 1, "Tower": 11, "Tree": 4, "Vehicle": 3, "Watercraft": 1, "Woman": 4}