{"Box": 1, "Boy": 2, "Chair": 1, "Clothing": 11, "Desk": 4, "Food": 1, "Footwear": 1, "Furniture": 4, "Houseplant": 2, "Human arm": 5, "Human body": 3, "Human eye": 2, "Human face": 3, "Human hair": 3, "Human hand": 3, "Human head": 3, "Human leg": 2, "Human nose": 2, "Jacket": 1, "Laptop": 2, "Lifejacket": 1, "Luggage and bags": 1, "Mammal": 2, "Man": 6, "Medical equipment": 2, "Office building": 1, "Office supplies": 2, "Person": 7, "Pillow": 1, "Plant": 5, "Printer": 1, "Shirt": 1, "Sports equipment": 1, "Sports uniform": 2, "Table": 6, "Wheel": 2, "Window": 1, "Woman": 2}