{"Aircraft": 1, "Airplane": 3, "Auto part": 2, "Bird": 8, "Boat": 4, "Book": 1, "Building": 2, "Car": 2, "Clothing": 1, "Envelope": 1, "Flag": 1, "Food": 4, "Fountain": 1, "Furniture": 1, "Helicopter": 1, "House": 4, "Human hair": 1, "Human head": 2, "Land vehicle": 7, "Mammal": 2, "Person": 1, "Picture frame": 2, "Plant": 7, "Poster": 5, "Snack": 1, "Swimming pool": 1, "Table": 1, "Tank": 1, "Tire": 1, "Toy": 1, "Train": 1, "Tree": 11, "Vehicle": 12, "Watercraft": 2, "Weapon": 1, "Wheel": 1, "Window": 2}