{"Auto part": 3, "Bird": 1, "Boat": 1, "Bowling equipment": 1, "Calculator": 1, "Camera": 2, "Car": 5, "Cassette deck": 1, "Clothing": 5, "Computer keyboard": 1, "Corded phone": 1, "Digital clock": 1, "Drill": 1, "Fish": 1, "Food": 2, "Footwear": 1, "Furniture": 1, "Handgun": 4, "Home appliance": 2, "Human arm": 7, "Human hand": 8, "Human leg": 3, "Ipod": 1, "Kitchen appliance": 1, "Land vehicle": 2, "Laptop": 2, "Mammal": 4, "Man": 3, "Medical equipment": 1, "Mobile phone": 4, "Office supplies": 2, "Person": 12, "Remote control": 1, "Rifle": 2, "Shotgun": 2, "Tablet computer": 1, "Toy": 1, "Vehicle": 2, "Weapon": 2, "Window": 4}