{"Aircraft": 1, "Airplane": 2, "Bicycle": 2, "Boy": 2, "Building": 1, "Cabinetry": 1, "Car": 1, "Chair": 3, "Clothing": 6, "Curtain": 3, "Door": 1, "Drum": 1, "Fashion accessory": 1, "Furniture": 4, "Girl": 1, "Glasses": 1, "Helicopter": 1, "House": 1, "Human arm": 7, "Human body": 2, "Human eye": 2, "Human face": 2, "Human hair": 3, "Human hand": 3, "Human head": 2, "Human leg": 1, "Human mouth": 1, "Human nose": 3, "Kitchen appliance": 1, "Land vehicle": 6, "Mammal": 2, "Man": 2, "Musical instrument": 1, "Office building": 1, "Office supplies": 1, "Person": 2, "Rifle": 1, "Sunglasses": 1, "Table": 1, "Toy": 2, "Vehicle": 5, "Weapon": 3, "Wheel": 1, "Wheelchair": 2, "Window": 7, "Woman": 2}