{"Aircraft": 1, "Airplane": 1, "Auto part": 1, "Billboard": 2, "Boat": 2, "Book": 1, "Bowling equipment": 1, "Box": 1, "Building": 1, "Car": 1, "Chair": 2, "Clothing": 8, "Computer monitor": 1, "Convenience store": 1, "Drink": 1, "Fast food": 4, "Food": 7, "Furniture": 4, "Girl": 2, "Human arm": 7, "Human body": 4, "Human face": 2, "Human hair": 2, "Human head": 2, "Human leg": 1, "Land vehicle": 2, "Man": 4, "Office supplies": 2, "Person": 8, "Picture frame": 1, "Poster": 2, "Snack": 4, "Swimming pool": 1, "Table": 3, "Television": 1, "Toy": 4, "Train": 1, "Vehicle": 3, "Watercraft": 1, "Window": 1, "Woman": 2}