{"Animal": 1, "Baked goods": 1, "Book": 1, "Boy": 2, "Cake": 1, "Cake stand": 1, "Clothing": 4, "Dog": 1, "Doll": 1, "Dress": 1, "Fashion accessory": 4, "Flag": 1, "Flower": 5, "Food": 5, "Furniture": 3, "Girl": 1, "Human arm": 13, "Human body": 1, "Human face": 1, "Human hair": 4, "Human hand": 9, "Human head": 3, "Human leg": 1, "Jacket": 1, "Mammal": 1, "Man": 3, "Person": 3, "Picture frame": 1, "Poster": 4, "Rose": 6, "Scarf": 1, "Sculpture": 1, "Shirt": 1, "Sports uniform": 2, "Table": 5, "Tableware": 1, "Toy": 2, "Tree": 1, "Vegetable": 1, "Woman": 1}