{"Billboard": 2, "Book": 2, "Bottle": 1, "Building": 2, "Candle": 2, "Clothing": 9, "Computer monitor": 1, "Doll": 1, "Dress": 2, "Fashion accessory": 6, "Flag": 1, "Food": 1, "Furniture": 1, "Girl": 1, "Home appliance": 1, "Human arm": 7, "Human body": 1, "Human eye": 4, "Human face": 3, "Human hair": 4, "Human hand": 2, "Human head": 2, "Human mouth": 3, "Human nose": 2, "Jacket": 1, "Land vehicle": 1, "Laptop": 1, "Mammal": 2, "Man": 3, "Mobile phone": 1, "Office supplies": 1, "Person": 6, "Picture frame": 1, "Poster": 4, "Scoreboard": 1, "Shelf": 1, "Shirt": 1, "Tablet computer": 1, "Television": 3, "Toy": 9, "Whiteboard": 1, "Woman": 1}