{"Billboard": 2, "Book": 1, "Bookcase": 1, "Boy": 3, "Building": 1, "Cabinetry": 1, "Clothing": 7, "Door": 2, "Dress": 1, "Filing cabinet": 1, "Flag": 4, "Furniture": 3, "Girl": 1, "House": 2, "Human arm": 4, "Human body": 2, "Human ear": 1, "Human eye": 1, "Human face": 2, "Human hair": 4, "Human head": 2, "Human leg": 1, "Human mouth": 3, "Human nose": 1, "Laptop": 1, "Mammal": 1, "Man": 4, "Medical equipment": 2, "Mirror": 2, "Nail": 1, "Office building": 1, "Office supplies": 1, "Person": 6, "Picture frame": 1, "Plant": 1, "Poster": 9, "Shelf": 1, "Shirt": 1, "Suit": 1, "Swimming pool": 1, "Table": 2, "Toy": 2, "Tree": 1, "Vehicle": 1, "Watercraft": 1, "Whiteboard": 4, "Window": 2, "Woman": 2}