{"Auto part": 1, "Billboard": 2, "Boat": 1, "Book": 1, "Boy": 1, "Building": 1, "Bus": 1, "Car": 3, "Clothing": 9, "Curtain": 1, "Door": 4, "Fashion accessory": 3, "Furniture": 3, "Human arm": 2, "Human body": 2, "Human ear": 2, "Human eye": 3, "Human face": 1, "Human hair": 3, "Human head": 1, "Human mouth": 1, "Human nose": 1, "Land vehicle": 5, "Mammal": 3, "Man": 5, "Mirror": 3, "Person": 7, "Picture frame": 6, "Poster": 3, "Shirt": 2, "Suit": 3, "Television": 1, "Tie": 1, "Train": 1, "Vehicle": 4, "Window": 8, "Woman": 1}