{"Ball": 1, "Book": 2, "Boy": 1, "Bronze sculpture": 1, "Building": 2, "Bust": 2, "Carnivore": 1, "Clothing": 7, "Cupboard": 1, "Curtain": 1, "Door": 3, "Door handle": 5, "Fashion accessory": 1, "Food": 3, "Footwear": 1, "Furniture": 2, "Girl": 2, "House": 2, "Human beard": 1, "Human body": 3, "Human ear": 2, "Human eye": 2, "Human face": 3, "Human hair": 4, "Human hand": 1, "Human head": 4, "Human mouth": 1, "Human nose": 1, "Lipstick": 1, "Mammal": 2, "Man": 3, "Mirror": 2, "Nail": 7, "Person": 6, "Picture frame": 2, "Plant": 1, "Poster": 2, "Refrigerator": 1, "Sculpture": 1, "Shelf": 2, "Shower": 4, "Tree": 1, "Wardrobe": 1, "Whiteboard": 1, "Window": 1, "Woman": 2}