{"Billboard": 5, "Bowling equipment": 1, "Building": 3, "Camera": 1, "Clothing": 6, "Computer monitor": 1, "Convenience store": 1, "Door": 8, "Furniture": 5, "Home appliance": 1, "Human arm": 2, "Human body": 3, "Human face": 3, "Human hair": 2, "Human head": 2, "Human leg": 1, "Kitchen appliance": 1, "Mammal": 3, "Man": 5, "Microwave oven": 1, "Office building": 1, "Person": 13, "Picture frame": 1, "Poster": 8, "Suit": 2, "Table": 1, "Television": 2, "Window": 14, "Woman": 2, "Wood-burning stove": 1}