{"Book": 1, "Boy": 2, "Building": 1, "Chair": 2, "Clothing": 6, "Curtain": 2, "Desk": 4, "Fashion accessory": 1, "Flag": 1, "Flower": 1, "Food": 1, "Furniture": 7, "Human arm": 6, "Human body": 3, "Human ear": 1, "Human eye": 8, "Human face": 4, "Human hair": 3, "Human head": 2, "Human mouth": 4, "Human nose": 1, "Jacket": 2, "Laptop": 5, "Mammal": 2, "Man": 4, "Office building": 2, "Office supplies": 6, "Person": 4, "Shirt": 2, "Sports uniform": 1, "Suit": 1, "Table": 7, "Vegetable": 2, "Woman": 1}