{"Alarm clock": 4, "Auto part": 2, "Billboard": 1, "Bowling equipment": 2, "Box": 2, "Building": 2, "Cabinetry": 1, "Car": 2, "Cassette deck": 3, "Computer keyboard": 1, "Computer monitor": 3, "Digital clock": 9, "Door": 5, "Drawer": 2, "Envelope": 1, "Filing cabinet": 2, "Flag": 1, "Furniture": 2, "Hand dryer": 2, "Home appliance": 3, "Kitchen appliance": 2, "Land vehicle": 1, "Laptop": 2, "Medical equipment": 3, "Microwave oven": 2, "Mirror": 1, "Mobile phone": 2, "Office supplies": 3, "Oven": 1, "Person": 2, "Picture frame": 4, "Poster": 6, "Refrigerator": 1, "Ruler": 1, "Scale": 2, "Scoreboard": 3, "Shelf": 1, "Tablet computer": 1, "Television": 3, "Vehicle": 1, "Washing machine": 1, "Watch": 2, "Whiteboard": 3, "Window": 2}