{"Billboard": 3, "Bowling equipment": 2, "Boy": 1, "Building": 6, "Clothing": 9, "Fashion accessory": 1, "Flag": 4, "Flower": 1, "Footwear": 3, "House": 1, "Human arm": 4, "Human body": 1, "Human eye": 4, "Human face": 1, "Human hair": 1, "Human hand": 2, "Human head": 1, "Human nose": 1, "Jacket": 1, "Jeans": 1, "Land vehicle": 1, "Lighthouse": 1, "Mammal": 1, "Man": 4, "Missile": 2, "Person": 10, "Poster": 4, "Rocket": 3, "Shirt": 1, "Shorts": 2, "Skyscraper": 5, "Sports uniform": 1, "Street light": 1, "Suit": 1, "Swimming pool": 2, "Television": 1, "Tower": 6, "Toy": 1, "Trousers": 2, "Vehicle": 2, "Window": 1}