{"Airplane": 1, "Animal": 6, "Auto part": 1, "Bat": 1, "Bird": 4, "Box": 1, "Briefcase": 1, "Butterfly": 1, "Camera": 1, "Car": 1, "Clothing": 1, "Fashion accessory": 1, "Fish": 2, "Flower": 6, "Food": 2, "Footwear": 4, "Handbag": 1, "Houseplant": 2, "Insect": 1, "Invertebrate": 2, "Land vehicle": 1, "Luggage and bags": 1, "Mammal": 3, "Mobile phone": 2, "Person": 2, "Plant": 40, "Plate": 1, "Power plugs and sockets": 1, "Saucer": 1, "Suitcase": 1, "Table": 1, "Tableware": 1, "Toy": 1, "Tree": 1, "Vegetable": 2, "Vehicle": 1}