{"Boy": 1, "Building": 1, "Candy": 1, "Christmas tree": 2, "Clothing": 10, "Convenience store": 1, "Flower": 21, "Food": 1, "Footwear": 1, "Girl": 1, "Glasses": 2, "Houseplant": 4, "Human arm": 2, "Human body": 1, "Human ear": 1, "Human eye": 4, "Human face": 1, "Human hair": 2, "Human head": 1, "Human mouth": 1, "Human nose": 1, "Jacket": 1, "Lantern": 1, "Mammal": 1, "Man": 1, "Microphone": 2, "Person": 6, "Plant": 7, "Poster": 1, "Pumpkin": 2, "Rose": 3, "Snack": 1, "Sports uniform": 1, "Toy": 9, "Tree": 2, "Woman": 2}