{"Aircraft": 3, "Airplane": 5, "Auto part": 16, "Baked goods": 1, "Boat": 4, "Building": 1, "Cake": 3, "Candy": 1, "Car": 9, "Cheese": 1, "Clothing": 1, "Dairy": 1, "Dessert": 1, "Fashion accessory": 1, "Food": 2, "Fruit": 1, "Furniture": 1, "Helicopter": 1, "Kitchen appliance": 1, "Land vehicle": 10, "Luggage and bags": 2, "Office supplies": 1, "Person": 1, "Skateboard": 1, "Snack": 1, "Suitcase": 1, "Table": 2, "Tableware": 1, "Tire": 2, "Toy": 2, "Train": 1, "Truck": 2, "Vehicle": 9, "Watercraft": 3, "Wheel": 6, "Window": 1}