{"Billboard": 1, "Boy": 1, "Bronze sculpture": 1, "Building": 2, "Christmas tree": 2, "Clothing": 7, "Fashion accessory": 1, "Flag": 1, "Flower": 5, "Footwear": 1, "Glasses": 1, "House": 3, "Houseplant": 2, "Human beard": 1, "Human body": 3, "Human eye": 2, "Human face": 5, "Human hair": 2, "Human head": 1, "Human mouth": 1, "Human nose": 1, "Mammal": 2, "Man": 4, "Palm tree": 15, "Person": 4, "Picture frame": 1, "Plant": 6, "Poster": 3, "Sculpture": 1, "Toy": 1, "Traffic sign": 1, "Tree": 10, "Vehicle": 1, "Window": 5, "Woman": 2}