{"Aircraft": 1, "Airplane": 1, "Auto part": 4, "Bottle": 1, "Car": 3, "Clothing": 7, "Computer keyboard": 1, "Computer monitor": 1, "Desk": 1, "Fashion accessory": 1, "Glasses": 14, "Goggles": 3, "Headphones": 4, "Human body": 1, "Human ear": 2, "Human face": 6, "Human hair": 4, "Human head": 2, "Human nose": 2, "Land vehicle": 4, "Laptop": 3, "Mammal": 1, "Man": 4, "Medical equipment": 2, "Office building": 1, "Person": 5, "Plate": 1, "Suit": 1, "Sunglasses": 5, "Tableware": 1, "Tool": 1, "Toy": 3, "Vehicle": 3, "Wheel": 6}