{"Airplane": 2, "Animal": 2, "Billboard": 3, "Bird": 2, "Boat": 1, "Boy": 1, "Building": 1, "Clothing": 7, "Dog": 3, "Fashion accessory": 2, "Flag": 2, "Flower": 1, "Food": 1, "Footwear": 11, "Girl": 1, "House": 1, "Human arm": 4, "Human body": 1, "Human face": 3, "Human hair": 2, "Human head": 2, "Human leg": 9, "Land vehicle": 1, "Mammal": 5, "Man": 2, "Person": 8, "Plant": 4, "Poster": 8, "Shorts": 1, "Sports equipment": 1, "Sports uniform": 1, "Traffic sign": 1, "Tree": 3, "Trousers": 1, "Vehicle": 1, "Woman": 1}