{"Airplane": 3, "Animal": 1, "Auto part": 3, "Baked goods": 1, "Billboard": 2, "Bird": 1, "Boat": 1, "Cake": 1, "Candy": 1, "Car": 4, "Clothing": 3, "Dairy": 1, "Dessert": 1, "Envelope": 1, "Flag": 3, "Flower": 1, "Food": 6, "Fountain": 2, "Furniture": 2, "House": 2, "Kite": 1, "Land vehicle": 5, "Mammal": 2, "Picture frame": 3, "Plant": 5, "Poster": 7, "Snack": 1, "Swimming pool": 2, "Table": 1, "Tart": 1, "Traffic sign": 2, "Tree": 16, "Umbrella": 2, "Vehicle": 7, "Watercraft": 2, "Window": 3}