{"Animal": 1, "Auto part": 1, "Bed": 2, "Billboard": 1, "Boy": 3, "Clothing": 7, "Couch": 2, "Dog": 1, "Door": 1, "Furniture": 3, "Girl": 3, "Human arm": 6, "Human body": 3, "Human eye": 4, "Human face": 3, "Human hair": 3, "Human hand": 3, "Human head": 2, "Human leg": 1, "Human mouth": 2, "Human nose": 7, "Land vehicle": 1, "Mammal": 4, "Man": 5, "Medical equipment": 2, "Person": 6, "Pillow": 4, "Plant": 1, "Poster": 2, "Sculpture": 1, "Sofa bed": 1, "Sports uniform": 2, "Tableware": 1, "Tire": 1, "Vehicle": 1, "Wheel": 1, "Window": 5, "Woman": 3}