{"Animal": 1, "Baked goods": 1, "Billboard": 1, "Book": 3, "Building": 2, "Butterfly": 1, "Cake": 2, "Closet": 1, "Clothing": 8, "Cookie": 1, "Crown": 1, "Curtain": 7, "Dairy": 1, "Dessert": 1, "Door": 2, "Dress": 1, "Fashion accessory": 1, "Fast food": 1, "Flag": 4, "Flower": 2, "Food": 2, "Fruit": 1, "Furniture": 1, "Hat": 1, "House": 1, "Human body": 1, "Man": 1, "Mirror": 1, "Pencil case": 1, "Person": 5, "Picture frame": 3, "Pineapple": 1, "Plant": 6, "Plate": 2, "Platter": 1, "Poster": 8, "Rose": 1, "Serving tray": 1, "Snack": 2, "Tableware": 1, "Television": 1, "Toy": 2, "Tree": 5, "Wheel": 2, "Whiteboard": 1, "Window": 5, "Woman": 1}