{"Auto part": 1, "Billboard": 3, "Book": 1, "Bowling equipment": 3, "Building": 1, "Chair": 2, "Clothing": 3, "Computer monitor": 13, "Desk": 5, "Door": 2, "Footwear": 1, "Furniture": 7, "Home appliance": 3, "Human face": 1, "Kitchen appliance": 1, "Land vehicle": 2, "Laptop": 4, "Medical equipment": 5, "Mirror": 1, "Office building": 1, "Office supplies": 3, "Person": 5, "Picture frame": 1, "Poster": 4, "Stool": 2, "Table": 6, "Telephone": 1, "Television": 5, "Tool": 1, "Traffic light": 1, "Treadmill": 2, "Vehicle": 2, "Whiteboard": 2, "Window": 5}